dsc/__init__.py
dsc/__main__.py
dsc/__query__.py
dsc/addict.py
dsc/constant.py
dsc/dsc_database.py
dsc/dsc_io.py
dsc/dsc_parser.py
dsc/dsc_translator.py
dsc/hdf5io.py
dsc/line.py
dsc/plugin.py
dsc/query_engine.py
dsc/query_jupyter.py
dsc/syntax.py
dsc/utils.py
dsc/version.py
dsc/yhat_sqldf.py
dsc/parser/__init__.py
dsc/parser/_nodes.py
dsc/parser/exceptions.py
dsc/parser/parser.py
dsc/parser/patterns.py
dsc/parser/utils.py
dsc-0.4.2.dist-info/LICENSE.txt
dsc-0.4.2.dist-info/METADATA
dsc-0.4.2.dist-info/WHEEL
dsc-0.4.2.dist-info/entry_points.txt
dsc-0.4.2.dist-info/top_level.txt
dsc-0.4.2.dist-info/RECORD
