Metadata-Version: 2.1
Name: dsc
Version: 0.4.2
Summary: Implementation of Dynamic Statistical Comparisons
Home-page: https://github.com/stephenslab/dsc
Author: Gao Wang
Author-email: gaow@uchicago.edu
License: MIT
Download-URL: https://pypi.python.org/pypi/dsc/0.4.2#downloads
Platform: UNKNOWN
Classifier: Development Status :: 3 - Alpha
Classifier: Environment :: Console
Classifier: License :: OSI Approved :: MIT License
Classifier: Natural Language :: English
Classifier: Operating System :: POSIX :: Linux
Classifier: Operating System :: MacOS :: MacOS X
Classifier: Intended Audience :: Science/Research
Classifier: Programming Language :: Python :: 3 :: Only
Requires-Dist: numpy
Requires-Dist: pandas (>=0.24.1)
Requires-Dist: sympy
Requires-Dist: numexpr
Requires-Dist: sos (>=0.21.5)
Requires-Dist: sos-pbs (>=0.20.3)
Requires-Dist: h5py
Requires-Dist: PTable
Requires-Dist: pyarrow (>=0.5.0)
Requires-Dist: sqlalchemy
Requires-Dist: tzlocal
Requires-Dist: msgpack-python
